{
    "AX": {
        "error": 0.004655631088323253, 
        "error_type": "SEM", 
        "filter_outliers_dict": {
            "filter_outliers": true, 
            "iterations": 1, 
            "std_devs": 2
        }, 
        "fit": "Average", 
        "fn": 115, 
        "include_baseline_error": false, 
        "n": 120, 
        "reviewed": true, 
        "value": 0.025238311461061643
    }, 
    "CDD": {
        "error": 2.717392774287108e-06, 
        "error_type": "SEM", 
        "filter_outliers_dict": {
            "filter_outliers": true, 
            "iterations": 1, 
            "std_devs": 10
        }, 
        "fit": "Average", 
        "fn": 120, 
        "include_baseline_error": false, 
        "n": 120, 
        "reviewed": true, 
        "value": 6.181046046549454e-06
    }, 
    "H1": {
        "error": 0.003646996684650568, 
        "error_type": "SEM", 
        "filter_outliers_dict": {
            "filter_outliers": true, 
            "iterations": 1, 
            "std_devs": 2
        }, 
        "fit": "Average", 
        "fn": 115, 
        "include_baseline_error": false, 
        "n": 120, 
        "reviewed": true, 
        "value": 0.02845431022844581
    }, 
    "H2": {
        "error": 0.009137136300575542, 
        "error_type": "SEM", 
        "filter_outliers_dict": {
            "filter_outliers": true, 
            "iterations": 1, 
            "std_devs": 2
        }, 
        "fit": "Average", 
        "fn": 115, 
        "include_baseline_error": false, 
        "n": 120, 
        "reviewed": true, 
        "value": 0.046442207315450776
    }, 
    "L1": {
        "error": 0.0019477391055102834, 
        "error_type": "SEM", 
        "filter_outliers_dict": {
            "filter_outliers": true, 
            "iterations": 1, 
            "std_devs": 2
        }, 
        "fit": "Average", 
        "fn": 116, 
        "include_baseline_error": false, 
        "n": 120, 
        "reviewed": true, 
        "value": -0.029583012968440268
    }, 
    "L2": {
        "error": 0.0043169662, 
        "error_type": "SEM", 
        "filter_outliers_dict": {
            "filter_outliers": true, 
            "iterations": 1, 
            "std_devs": 2
        }, 
        "fit": "average", 
        "value": -0.0395830577
    }
}