{
    "Ar36": {
        "error": 0.00011358738587064069,
        "error_type": "SEM",
        "filter_outliers_dict": {
            "filter_outliers": true,
            "iterations": 1,
            "std_devs": 2
        },
        "fit": "Linear",
        "fn": 273,
        "include_baseline_error": false,
        "n": 280,
        "reviewed": true,
        "value": 0.003805704950107989
    },
    "Ar37": {
        "error": 0.005989733398118148,
        "error_type": "SEM",
        "filter_outliers_dict": {
            "filter_outliers": true,
            "iterations": 1,
            "std_devs": 2
        },
        "fit": "Linear",
        "fn": 270,
        "include_baseline_error": false,
        "n": 280,
        "reviewed": true,
        "value": -0.00937153056970462
    },
    "Ar38": {
        "error": 0.0025057719204977682,
        "error_type": "SEM",
        "filter_outliers_dict": {
            "filter_outliers": true,
            "iterations": 1,
            "std_devs": 2
        },
        "fit": "Linear",
        "fn": 267,
        "include_baseline_error": false,
        "n": 280,
        "reviewed": true,
        "value": -0.02975415124870995
    },
    "Ar39": {
        "error": 0.006074598781553299,
        "error_type": "SEM",
        "filter_outliers_dict": {
            "filter_outliers": true,
            "iterations": 1,
            "std_devs": 2
        },
        "fit": "Linear",
        "fn": 263,
        "include_baseline_error": false,
        "n": 280,
        "reviewed": true,
        "value": 0.014484071887091467
    },
    "Ar40": {
        "error": 0.00788158188011091,
        "error_type": "SEM",
        "filter_outliers_dict": {
            "filter_outliers": true,
            "iterations": 1,
            "std_devs": 2
        },
        "fit": "Linear",
        "fn": 271,
        "include_baseline_error": false,
        "n": 280,
        "reviewed": true,
        "value": 0.8281816655621836
    },
    "Ar41": {
        "error": 0.014078775725323305,
        "error_type": "SEM",
        "filter_outliers_dict": {
            "filter_outliers": true,
            "iterations": 1,
            "std_devs": 2
        },
        "fit": "linear",
        "value": 0.0686454337045522
    }
}