{
    "Ar36": {
        "error": 0.00023630346089385603,
        "error_type": "SEM",
        "filter_outliers_dict": {
            "filter_outliers": true,
            "iterations": 1,
            "std_devs": 2
        },
        "fit": "Parabolic",
        "fn": 274,
        "include_baseline_error": false,
        "n": 280,
        "reviewed": true,
        "value": 0.005475056171773317
    },
    "Ar37": {
        "error": 0.0055045825340849855,
        "error_type": "SEM",
        "filter_outliers_dict": {
            "filter_outliers": true,
            "iterations": 1,
            "std_devs": 2
        },
        "fit": "Linear",
        "fn": 266,
        "include_baseline_error": false,
        "n": 280,
        "reviewed": true,
        "value": -0.01723343624592522
    },
    "Ar38": {
        "error": 0.0027137141873606386,
        "error_type": "SEM",
        "filter_outliers_dict": {
            "filter_outliers": true,
            "iterations": 1,
            "std_devs": 2
        },
        "fit": "Linear",
        "fn": 268,
        "include_baseline_error": false,
        "n": 280,
        "reviewed": true,
        "value": -0.030188354743760422
    },
    "Ar39": {
        "error": 0.011620445022698536,
        "error_type": "SEM",
        "filter_outliers_dict": {
            "filter_outliers": true,
            "iterations": 1,
            "std_devs": 2
        },
        "fit": "Parabolic",
        "fn": 265,
        "include_baseline_error": false,
        "n": 280,
        "reviewed": true,
        "value": 0.00014989926989397544
    },
    "Ar40": {
        "error": 0.01841088578337693,
        "error_type": "SEM",
        "filter_outliers_dict": {
            "filter_outliers": true,
            "iterations": 1,
            "std_devs": 2
        },
        "fit": "Linear",
        "fn": 271,
        "include_baseline_error": false,
        "n": 280,
        "reviewed": true,
        "value": 1.3279783013977497
    },
    "Ar41": {
        "error": 0.014387973177733568,
        "error_type": "SEM",
        "filter_outliers_dict": {
            "filter_outliers": true,
            "iterations": 1,
            "std_devs": 2
        },
        "fit": "linear",
        "value": 0.0493276901876746
    }
}